MANIFEST.in
README.md
setup.cfg
setup.py
deep_pipeline.egg-info/PKG-INFO
deep_pipeline.egg-info/SOURCES.txt
deep_pipeline.egg-info/dependency_links.txt
deep_pipeline.egg-info/not-zip-safe
deep_pipeline.egg-info/requires.txt
deep_pipeline.egg-info/top_level.txt
deeppipeline/__init__.py
deeppipeline/common/__init__.py
deeppipeline/common/core.py
deeppipeline/common/dataset.py
deeppipeline/common/evaluation.py
deeppipeline/common/losses.py
deeppipeline/common/modules.py
deeppipeline/common/normalization.py
deeppipeline/common/transforms.py
deeppipeline/common/_robustloss/__init__.py
deeppipeline/common/_robustloss/adaptiveloss.py
deeppipeline/common/_robustloss/cubic_spline.py
deeppipeline/common/_robustloss/distribution.py
deeppipeline/common/_robustloss/general.py
deeppipeline/common/_robustloss/util.py
deeppipeline/common/_robustloss/data/partition_spline.npz
deeppipeline/io/__init__.py
deeppipeline/io/_io.py
deeppipeline/keypoints/__init__.py
deeppipeline/keypoints/models/__init__.py
deeppipeline/keypoints/models/_hourglass.py
deeppipeline/keypoints/models/modules.py
deeppipeline/kvs/__init__.py
deeppipeline/kvs/_kvs.py
deeppipeline/segmentation/__init__.py
deeppipeline/segmentation/evaluation/__init__.py
deeppipeline/segmentation/evaluation/_utils.py
deeppipeline/segmentation/evaluation/metrics.py
deeppipeline/segmentation/evaluation/tta.py
deeppipeline/segmentation/losses/__init__.py
deeppipeline/segmentation/losses/_functions.py
deeppipeline/segmentation/losses/_losses.py
deeppipeline/segmentation/models/__init__.py
deeppipeline/segmentation/models/_functions.py
deeppipeline/segmentation/models/_unet.py
deeppipeline/segmentation/models/modules.py
deeppipeline/segmentation/training/__init__.py
deeppipeline/segmentation/training/core.py
deeppipeline/segmentation/training/dataset.py
deeppipeline/transforms/__init__.py
deeppipeline/transforms/segmentation.py