Metadata-Version: 1.1
Name: deep-pipeline
Version: 0.2.5
Summary: Building blocks for Deep Learning
Home-page: https://github.com/lext/deep-pipeline
Author: Aleksei Tiulpin
Author-email: aleksei.tiulpin@oulu.fi
License: MIT license
Keywords: deeep learning,image segmentation,image-classification
Platform: UNKNOWN
Classifier: Development Status :: 5 - Production/Stable
Classifier: Intended Audience :: Science/Research
Classifier: Intended Audience :: Developers
Classifier: License :: OSI Approved :: MIT License
Classifier: Natural Language :: English
Classifier: Programming Language :: Python :: 3.6
Classifier: Programming Language :: Python :: 3.7
Classifier: Operating System :: MacOS
Classifier: Operating System :: POSIX :: Linux
